{"date": "2018-01-17_21:33:45", "url": "http://www.eurekalert.org/pub_releases/2017-05/uoth-nus050817.php", "year": "Mon, 08 May 2017 04:00:00 GMT", "text": ["experimental", "biology", "2017april", "22", "26", "2017chicago", "il2018", "aaas", "annual", "meeting", "february", "15", "19", "2018austin", "txhouston", "may", "8", "2017", "clinical", "trial", "drug", "researchers", "hope", "prevent", "delay", "onset", "epilepsy", "children", "tuberous", "sclerosis", "begun", "mcgovern", "medical", "school", "university", "texas", "health", "science", "center", "houston", "uthealth", "houston", "site", "one", "seven", "country", "led", "mary", "koenig", "associate", "professor", "endowed", "chair", "mitochondrial", "medicine", "division", "neurology", "department", "pediatrics", "mcgovern", "medical", "school", "uthealth", "could", "potentially", "epilepsy", "general", "first", "trial", "ever", "aimed", "preventing", "seizures", "developing", "vulnerable", "population", "koenig", "sclerosis", "complex", "tsc", "genetic", "disorder", "causes", "tumors", "form", "many", "different", "organs", "including", "brain", "affect", "neurologic", "functions", "leading", "seizures", "developmental", "delay", "intellectual", "disability", "autism", "according", "published", "research", "harvard", "80", "percent", "children", "tsc", "develop", "epilepsy", "within", "first", "three", "years", "national", "institutes", "health", "clinical", "trial", "recruit", "total", "80", "infants", "tsc", "first", "sign", "abnormal", "brain", "activity", "revealed", "electroencephalogram", "half", "infants", "receive", "vigabatrin", "medication", "used", "control", "infantile", "spasms", "half", "receive", "placebo", "onset", "clinical", "seizures", "children", "transition", "standard", "care", "infants", "tsc", "seizures", "investigators", "follow", "children", "three", "years", "monitor", "developmental", "progress", "onset", "severity", "study", "called", "preventing", "epilepsy", "using", "vigabatrin", "infants", "tuberous", "sclerosis", "complex", "target", "window", "time", "abnormal", "brain", "activity", "onset", "seizures", "usually", "two", "three", "months", "researchers", "hoping", "determine", "whether", "early", "intervention", "positive", "effect", "developmental", "outcomes", "delay", "prevent", "onset", "seizures"], "title": "New UTHealth study focuses on treatment for epilepsy caused by tuberous sclerosis | EurekAlert! Science News", "source": "University of Texas Health Science Center at Houston"}