{"authors": [["Valensi", "Paul", "P", "Department of Endocrinology Diabetology Nutrition, Jean Verdier Hospital, APHP, CRNH-IdF, CINFO, Paris Nord University, Bondy Cedex, France."], ["Husemoen", "Lise Lotte N", "LLN", "Novo Nordisk A/S, Copenhagen, Denmark."], ["Weatherall", "James", "J", "Novo Nordisk Inc., Princeton, NJ, USA."], ["Monnier", "Louis", "L", "Institute of Clinical Research, University of Montpellier, Montpellier, France."]], "text": "", "id": "29283504", "date": null, "title": "Association of postprandial and fasting plasma glucose with HbA1c across the spectrum of glycaemic impairment in type 2 diabetes.", "doi": "10.1111/ijcp.13041", "journal": ["International journal of clinical practice", "Int. J. Clin. Pract."]}