{"authors": [["Eid", "Ahmad M", "AM", "Center for Autism Research, King Faisal Specialist Hospital & Research Center, Riyadh, Saudi Arabia."], ["Aljaser", "Sarah M", "SM", "Center for Autism Research, King Faisal Specialist Hospital & Research Center, Riyadh, Saudi Arabia."], ["AlSaud", "Anoud N", "AN", "Center for Autism Research, King Faisal Specialist Hospital & Research Center, Riyadh, Saudi Arabia."], ["Asfahani", "Sultana M", "SM", "Center for Autism Research, King Faisal Specialist Hospital & Research Center, Riyadh, Saudi Arabia."], ["Alhaqbani", "Ohoud A", "OA", "Center for Autism Research, King Faisal Specialist Hospital & Research Center, Riyadh, Saudi Arabia."], ["Mohtasib", "Rafat S", "RS", "Center for Autism Research, King Faisal Specialist Hospital & Research Center, Riyadh, Saudi Arabia."], ["Aldhalaan", "Hesham M", "HM", "Center for Autism Research, King Faisal Specialist Hospital & Research Center, Riyadh, Saudi Arabia."], ["Fryling", "Mitch", "M", "California State University, Los Angeles, USA."]], "doi": "10.1007/s40617-016-0167-3", "date": "2018-01-16_23:19:15", "journal": ["Behavior analysis in practice", "Behav Anal Pract"], "year": null, "title": "Training Parents in Saudi Arabia to Implement Discrete Trial Teaching with their Children with Autism Spectrum Disorder.", "id": "29214136", "text": ["present", "study", "evaluates", "effects", "behavioral", "skill", "training", "package", "parent", "implementation", "discrete", "trial", "teaching", "children", "autism", "spectrum", "disorder", "three", "mothers", "children", "autism", "participated", "study", "training", "package", "improved", "implementation", "three", "mothers", "moreover", "improvements", "generalized", "skills", "taught", "training", "maintained", "probes", "resulted", "improvements", "child", "behavior"]}